iAnnotateSV/AddExternalAnnotations.py
iAnnotateSV/AnnotateEachBreakpoint.py
iAnnotateSV/AnnotateForCosmic.py
iAnnotateSV/AnnotateForDGv.py
iAnnotateSV/AnnotateForRepeatRegion.py
iAnnotateSV/AnnotationForKinaseDomain.py
iAnnotateSV/FindCanonicalTranscript.py
iAnnotateSV/FindTranscript.py
iAnnotateSV/PredictFunction.py
iAnnotateSV/VisualizeSV.py
iAnnotateSV/__init__.py
iAnnotateSV/data/UcscUniprotdomainInfo/hg19.uniprot.spAnnot.table.txt
iAnnotateSV/data/canonicalInfo/canonical_transcripts.txt
iAnnotateSV/data/canonicalInfo/canonical_transcripts_cv5.txt
iAnnotateSV/data/canonicalInfo/canonical_transcripts_cv6.txt
iAnnotateSV/data/cosmic/CosmicConsensus_transFeb2014.tsv
iAnnotateSV/data/cosmic/cancer_gene_census.tsv
iAnnotateSV/data/cosmic/cosmic_fusion_counts.tsv
iAnnotateSV/data/database_of_genomic_variants/hg19_DGv_Annotation.tsv
iAnnotateSV/data/references/hg18.sv.table.txt
iAnnotateSV/data/references/hg19.sv.table.txt
iAnnotateSV/data/references/hg38.sv.table.txt
iAnnotateSV/data/repeat_region/hg19_repeatRegion.tsv
iAnnotateSV/data/test/.DS_Store
iAnnotateSV/data/test/bigTestData.txt
iAnnotateSV/data/test/testData.txt
iAnnotateSV/helper.py
iAnnotateSV/iAnnotateSV.py
iAnnotateSV/models.py
iAnnotateSV/test/__init__.py
iAnnotateSV/test/testResult_Annotated.txt
iAnnotateSV/test/test_iAnnotateSVs.py
iannotatesv-1.3.0.dist-info/LICENSE.txt
iannotatesv-1.3.0.dist-info/METADATA
iannotatesv-1.3.0.dist-info/WHEEL
iannotatesv-1.3.0.dist-info/entry_points.txt
iannotatesv-1.3.0.dist-info/RECORD
