Metadata-Version: 2.1
Name: iAnnotateSV
Version: 1.3.0
Summary: iAnnotateSV is a Python library and command-line software toolkit to annotate and visualize structural variants detected from Next Generation DNA sequencing data.
Author: Ronak Shah
Author-email: shahr2@mskcc.org
Requires-Python: >=3.10,<4.0
Classifier: Programming Language :: Python :: 3
Classifier: Programming Language :: Python :: 3.10
Classifier: Programming Language :: Python :: 3.11
Classifier: Programming Language :: Python :: 3.12
Requires-Dist: biopython (==1.84)
Requires-Dist: coloredlogs (==15.0.1)
Requires-Dist: numpy (==2.1.0)
Requires-Dist: openpyxl (==3.1.5)
Requires-Dist: pandas (==2.2.2)
Requires-Dist: pillow (==10.4.0)
Requires-Dist: reportlab (==3.6.13)
